dmxpy/DmxPy.py
dmxpy/__init__.py
DmxPy-0.4.dist-info/LICENSE
DmxPy-0.4.dist-info/METADATA
DmxPy-0.4.dist-info/WHEEL
DmxPy-0.4.dist-info/entry_points.txt
DmxPy-0.4.dist-info/top_level.txt
DmxPy-0.4.dist-info/RECORD
