Metadata-Version: 2.1
Name: DmxPy
Version: 0.4
Summary: DMX USB Pro compatible controller
Home-page: https://github.com/itsb/DmxPy
Author: itsb
License: MIT License
Keywords: DMX USB Lighting
Platform: UNKNOWN
Classifier: Programming Language :: Python
Classifier: License :: OSI Approved :: MIT License
Classifier: Operating System :: OS Independent
Classifier: Environment :: Console
Requires-Dist: pyserial
